lifedata/__init__.py
lifedata/alembic.ini
lifedata/__pycache__/__init__.cpython-310.pyc
lifedata/__pycache__/__init__.cpython-37.pyc
lifedata/__pycache__/__init__.cpython-38.pyc
lifedata/__pycache__/__init__.cpython-39.pyc
lifedata/annotations/__init__.py
lifedata/annotations/annotation.py
lifedata/annotations/annotation_count.py
lifedata/annotations/annotation_service.py
lifedata/annotations/annotator.py
lifedata/annotations/assignment.py
lifedata/annotations/authentication.py
lifedata/annotations/consultation.py
lifedata/annotations/events.py
lifedata/annotations/queriedsample.py
lifedata/annotations/sample.py
lifedata/annotations/sample_repository.py
lifedata/annotations/skip.py
lifedata/annotations/__pycache__/__init__.cpython-310.pyc
lifedata/annotations/__pycache__/__init__.cpython-37.pyc
lifedata/annotations/__pycache__/__init__.cpython-38.pyc
lifedata/annotations/__pycache__/__init__.cpython-39.pyc
lifedata/annotations/__pycache__/annotation.cpython-310.pyc
lifedata/annotations/__pycache__/annotation.cpython-37.pyc
lifedata/annotations/__pycache__/annotation.cpython-38.pyc
lifedata/annotations/__pycache__/annotation.cpython-39.pyc
lifedata/annotations/__pycache__/annotation_count.cpython-310.pyc
lifedata/annotations/__pycache__/annotation_count.cpython-38.pyc
lifedata/annotations/__pycache__/annotation_count.cpython-39.pyc
lifedata/annotations/__pycache__/annotation_service.cpython-310.pyc
lifedata/annotations/__pycache__/annotation_service.cpython-37.pyc
lifedata/annotations/__pycache__/annotation_service.cpython-38.pyc
lifedata/annotations/__pycache__/annotation_service.cpython-39.pyc
lifedata/annotations/__pycache__/annotator.cpython-310.pyc
lifedata/annotations/__pycache__/annotator.cpython-37.pyc
lifedata/annotations/__pycache__/annotator.cpython-38.pyc
lifedata/annotations/__pycache__/annotator.cpython-39.pyc
lifedata/annotations/__pycache__/assignment.cpython-310.pyc
lifedata/annotations/__pycache__/assignment.cpython-37.pyc
lifedata-0.1.1.dist-info/LICENSE.md
lifedata-0.1.1.dist-info/METADATA
lifedata-0.1.1.dist-info/WHEEL
lifedata-0.1.1.dist-info/entry_points.txt
lifedata-0.1.1.dist-info/top_level.txt
lifedata-0.1.1.dist-info/RECORD
