Metadata-Version: 2.1
Name: lifedata
Version: 0.1.1
Summary: A Python Framework for Tracable Active Learning Projects.
Author: DS Lab, University of Augsburg
Maintainer: LIFEDATA Research Group
Project-URL: Homepage, https://github.com/ds-lab/lifedata
Project-URL: Bug Tracker, https://github.com/ds-lab/lifedata/issues
Classifier: Programming Language :: Python :: 3
Classifier: Operating System :: OS Independent
Requires-Python: >=3.10
License-File: LICENSE.md
Requires-Dist: alembic
Requires-Dist: aiofiles
Requires-Dist: click
Requires-Dist: cookiecutter
Requires-Dist: fastapi
Requires-Dist: honcho
Requires-Dist: pyjwt
Requires-Dist: pandas
Requires-Dist: loguru
Requires-Dist: numpy
Requires-Dist: orjson
Requires-Dist: pydantic
Requires-Dist: psycopg2-binary
Requires-Dist: sqlalchemy
Requires-Dist: toolz
Requires-Dist: uvicorn
Provides-Extra: dev
Requires-Dist: black ; extra == 'dev'
Requires-Dist: hypothesis ; extra == 'dev'
Requires-Dist: pytest ; extra == 'dev'
Requires-Dist: pytest-cov ; extra == 'dev'
Requires-Dist: requests ; extra == 'dev'
